[
    {
        "iconUrl": "https://www.google.com/s2/favicons?domain=animehay.in&sz=%size%",
        "apiVersion": 1,
        "repositoryUrl": "https://t.me/cloudstream_extension_vn",
        "fileSize": 17742,
        "status": 1,
        "authors": [
            "anhdaden"
        ],
        "tvTypes": [
            "Anime"
        ],
        "version": 11,
        "internalName": "AnimeHayProvider",
        "url": "https://abyss-api-two.vercel.app/download?folder=anime&file=AnimeHayProvider_1733393561.cs3",
        "name": "AnimeHayProvider"
    },
    {
        "iconUrl": "https://www.google.com/s2/favicons?domain=animevietsub.app&sz=%size%",
        "apiVersion": 1,
        "repositoryUrl": "https://t.me/cloudstream_extension_vn",
        "fileSize": 21595,
        "status": 1,
        "authors": [
            "anhdaden"
        ],
        "tvTypes": [
            "Anime"
        ],
        "version": 13,
        "internalName": "AnimeVietsubProvider",
        "url": "https://abyss-api-two.vercel.app/download?folder=anime&file=AnimeVietsubProvider_1733393561.cs3",
        "name": "AnimeVietsubProvider"
    },
    {
        "iconUrl": "https://play-lh.googleusercontent.com/TOTj0uMWp7cXkjXDXkcTZnPigUmpLRRiH956lHRJxStlY7ucxmtwMs_Kr2wOWYm0fSY=w240-h480-rw",
        "apiVersion": 1,
        "repositoryUrl": "https://t.me/cloudstream_extension_vn",
        "fileSize": 102150,
        "status": 1,
        "authors": [
            "anhdaden"
        ],
        "tvTypes": [
            "Anime",
            "TvSeries",
            "Movie"
        ],
        "version": 24,
        "internalName": "FshareProvider",
        "description": "Download FullHD, 2K, 4K with Fshare Vip account",
        "url": "https://gitlab.com/tearrs/cloudstream-vietnamese/-/raw/main/FshareProvider.cs3",
        "name": "FshareProvider"
    },
    {
        "iconUrl": "https://www.google.com/s2/favicons?domain=hhkungfu.shop&sz=%size%",
        "apiVersion": 1,
        "repositoryUrl": "https://t.me/cloudstream_extension_vn",
        "fileSize": 20359,
        "status": 1,
        "authors": [
            "anhdaden"
        ],
        "tvTypes": [
            "Anime",
            "AnimeMovie"
        ],
        "version": 5,
        "internalName": "HHkungfuProvider",
        "description": "Ho\u1ea1t h\u00ecnh Trung Qu\u1ed1c vietsub",
        "url": "https://abyss-api-two.vercel.app/download?folder=anime&file=HHkungfuProvider_1733393561.cs3",
        "name": "HHkungfuProvider"
    },
    {
        "iconUrl": "https://www.google.com/s2/favicons?domain=hhpanda.tube&sz=%size%",
        "apiVersion": 1,
        "repositoryUrl": "https://t.me/cloudstream_extension_vn",
        "fileSize": 17645,
        "status": 1,
        "authors": [
            "anhdaden"
        ],
        "tvTypes": [
            "Anime"
        ],
        "version": 11,
        "internalName": "HHPandaProvider",
        "description": "Anime, Ho\u1ea1t h\u00ecnh Trung Qu\u1ed1c",
        "url": "https://abyss-api-two.vercel.app/download?folder=anime&file=HHPandaProvider_1733393561.cs3",
        "name": "HHPandaProvider"
    },
    {
        "iconUrl": "https://yanhh3d.net/storage/settings/August2024/YOoAwtlobLbwKhiFwRZv.png",
        "apiVersion": 1,
        "repositoryUrl": "https://t.me/cloudstream_extension_vn",
        "fileSize": 32844,
        "status": 1,
        "authors": [
            "anhdaden"
        ],
        "tvTypes": [
            "Anime",
            "AnimeMovie"
        ],
        "version": 16,
        "internalName": "YanHH3DProvider",
        "description": "Ho\u1ea1t h\u00ecnh Trung Qu\u1ed1c thuy\u1ebft minh",
        "url": "https://gitlab.com/tearrs/movie/-/raw/main/YanHH3DProvider.cs3",
        "name": "YanHH3DProvider"
    }
]
